MANIFEST.in
README.txt
setup.py
rstex.egg-info/PKG-INFO
rstex.egg-info/SOURCES.txt
rstex.egg-info/dependency_links.txt
rstex.egg-info/not-zip-safe
rstex.egg-info/requires.txt
rstex.egg-info/top_level.txt
src/rstex.py
test/long.rst
test/references.bib
test/short.log
test/short.rst