Metadata-Version: 1.0
Name: rstex
Version: 0.12
Summary: An extension of docutils' rst2latex with inline math, equations, references, and raw latex
Home-page: http://muralab.org/rstex
Author: Marcin Cieslik
Author-email: mpc4p@virginia.edu
License: BSD License
Keywords: restructuredtext rst docutils latex tex math rst2latex
Platform: UNKNOWN
